flask_sitemap/__init__.py
flask_sitemap/cli.py
flask_sitemap/config.py
flask_sitemap/version.py
flask_sitemap/templates/flask_sitemap/sitemap.xml
flask_sitemap/templates/flask_sitemap/sitemapindex.xml
Flask_Sitemap-0.4.0.dist-info/AUTHORS
Flask_Sitemap-0.4.0.dist-info/LICENSE
Flask_Sitemap-0.4.0.dist-info/METADATA
Flask_Sitemap-0.4.0.dist-info/WHEEL
Flask_Sitemap-0.4.0.dist-info/top_level.txt
Flask_Sitemap-0.4.0.dist-info/RECORD
