Metadata-Version: 2.1
Name: Flask-Sitemap
Version: 0.4.0
Summary: Flask extension that helps with sitemap generation.
Home-page: http://github.com/inveniosoftware/flask-sitemap/
Author: Invenio collaboration
Author-email: info@inveniosoftware.org
License: BSD
Platform: any
Classifier: Environment :: Web Environment
Classifier: Intended Audience :: Developers
Classifier: License :: OSI Approved :: BSD License
Classifier: Operating System :: OS Independent
Classifier: Programming Language :: Python
Classifier: Framework :: Flask
Classifier: Topic :: Internet :: WWW/HTTP :: Dynamic Content
Classifier: Topic :: Software Development :: Libraries :: Python Modules
Classifier: Programming Language :: Python :: 3
Classifier: Programming Language :: Python :: 3.6
Classifier: Programming Language :: Python :: 3.7
Classifier: Programming Language :: Python :: 3.8
Classifier: Programming Language :: Python :: 3.9
Classifier: Programming Language :: Python :: 3.10
Classifier: Development Status :: 5 - Production/Stable
Provides-Extra: docs
Provides-Extra: tests
Provides-Extra: all
